{
    "basic_info": {
      "name": "Erlanga Dwi Permadi",
      "titles": [ "keep learning other programming languages" ],
      "social": [
        {
          "name": "github",
          "url": "https://github.com/erdwpe",
          "class": "fab fa-github"
        },
        {
          "name": "instagram",
          "url": "https://www.instagram.com/erdwpe",
          "class": "fab fa-instagram"
        }
      ],
      "image": "F72314-EB-CC3-F-48-AE-9352-7-A901-A6446-B1.jpg"
    },
    "skills": {
      "icons": [
        {
          "name": "HTML 5",
          "class": "devicon-html5-plain",
          "level": "95"
        },
        {
          "name": "CSS 3",
          "class": "devicon-css3-plain",
          "level": "95"
        },
        {
          "name": "JavaScript",
          "class": "devicon-javascript-plain",
          "level": "70"
        },
        {
          "name": "Bootstrap",
          "class": "devicon-bootstrap-plain",
          "level": "85"
        }
      ]
    }
  }